Uxagent/__init__.py
Uxagent/filters.py
Uxagent/uxagent.py
Uxagent/data/user_agents.zip
uxagent-0.1.4.dist-info/LICENSE
uxagent-0.1.4.dist-info/METADATA
uxagent-0.1.4.dist-info/WHEEL
uxagent-0.1.4.dist-info/top_level.txt
uxagent-0.1.4.dist-info/RECORD
